{
    "paths": {
        "4eeMFSptJO16KtzTB5ehB4": [
            "1",
            "cc.Texture2D"
        ],
        "acKpgN64xDXaZowa8i3vOM": [
            "1",
            "cc.SpriteFrame",
            1
        ],
        "0d8BDS4TVMqIrXgAeDsDZ8": [
            "10",
            "cc.Texture2D"
        ],
        "90p4iHfM5OC43LiybWaRKL": [
            "10",
            "cc.SpriteFrame",
            1
        ],
        "f7YOiOWV5NtJegf7GZRQiw": [
            "11",
            "cc.SpriteFrame",
            1
        ],
        "fcSD5HxXdFUpXBfnlIF/tT": [
            "11",
            "cc.Texture2D"
        ],
        "3cFfAVcS5CILS8vlSS3NDZ": [
            "12",
            "cc.Texture2D"
        ],
        "4aBvlIQeNK2IOBWmvKFO/m": [
            "12",
            "cc.SpriteFrame",
            1
        ],
        "d3BkeJwEZJaaXSHGAi2MrT": [
            "13",
            "cc.SpriteFrame",
            1
        ],
        "f3am8IdzhA2ayzpz6KNhPO": [
            "13",
            "cc.Texture2D"
        ],
        "9blsOIbrJIDKXRWtsW+jp1": [
            "14",
            "cc.SpriteFrame",
            1
        ],
        "f2RoUEDfNAq7vEst/bvQ9e": [
            "14",
            "cc.Texture2D"
        ],
        "1desLl4yhMka6fDT1yk90+": [
            "15",
            "cc.SpriteFrame",
            1
        ],
        "66PVO8gr1IWbsPgcLgpNTy": [
            "15",
            "cc.Texture2D"
        ],
        "5d1E5yx/BEG4SS6TLAWvW7": [
            "16",
            "cc.Texture2D"
        ],
        "98fK1Lq+FJAoRX+ZNGzb2j": [
            "16",
            "cc.SpriteFrame",
            1
        ],
        "04rbNfI4BAB4g2Cf863T3l": [
            "17",
            "cc.Texture2D"
        ],
        "b3871/jfBLMq96icCHyRzW": [
            "17",
            "cc.SpriteFrame",
            1
        ],
        "37voB+GNtJxqSy+7sneKHM": [
            "18",
            "cc.Texture2D"
        ],
        "c3VjjUGW9B1ZhB45LePwCF": [
            "18",
            "cc.SpriteFrame",
            1
        ],
        "79oDw3Zm9IWaRk3EXpwRli": [
            "19",
            "cc.Texture2D"
        ],
        "79o3/Dd9VBvKaoCvNyDCrY": [
            "19",
            "cc.SpriteFrame",
            1
        ],
        "029mfSeWdPUYrFiz8NBEjw": [
            "2",
            "cc.SpriteFrame",
            1
        ],
        "64B7iS10pPMLYexhWjtQxU": [
            "2",
            "cc.Texture2D"
        ],
        "48wUeKRBhGkpdXuN4MI8UM": [
            "20",
            "cc.SpriteFrame",
            1
        ],
        "d58n5dGu5Kn4BbTb5V4Efn": [
            "20",
            "cc.Texture2D"
        ],
        "15IKLnjE5Pna+2Gxh7gNJh": [
            "21",
            "cc.Texture2D"
        ],
        "efDPacnAVLpoQ5S0Ovh1Nv": [
            "21",
            "cc.SpriteFrame",
            1
        ],
        "1c/GOmZglBn4LHA7+TTXy7": [
            "22",
            "cc.Texture2D"
        ],
        "c4P3/88sdFvKlp10TpQhd3": [
            "22",
            "cc.SpriteFrame",
            1
        ],
        "10rv5DqDJIGL46tTev8SCq": [
            "23",
            "cc.SpriteFrame",
            1
        ],
        "b3UKt2Z2xKYIC9E9/uxu9i": [
            "23",
            "cc.Texture2D"
        ],
        "67BMUMPHlEUrV8gmysFDP6": [
            "24",
            "cc.Texture2D"
        ],
        "d4sy5LaHNKVp4A9DeZg3yq": [
            "24",
            "cc.SpriteFrame",
            1
        ],
        "7aoEcDVHFEUYN9aBpYO9oL": [
            "25",
            "cc.SpriteFrame",
            1
        ],
        "edNqTdobFC9Knh8IuotWbn": [
            "25",
            "cc.Texture2D"
        ],
        "58CLvVCTFLzpAswP5irm/d": [
            "26",
            "cc.SpriteFrame",
            1
        ],
        "c2Tn9h6aBC9ppfBhyaUO7A": [
            "26",
            "cc.Texture2D"
        ],
        "32/qRABfZBlbui8CMzxz5l": [
            "27",
            "cc.SpriteFrame",
            1
        ],
        "9eM3vLGlhAsreCsrG1DQ0M": [
            "27",
            "cc.Texture2D"
        ],
        "5btAs+DXVKjJ9LyOs+MUxI": [
            "28",
            "cc.SpriteFrame",
            1
        ],
        "61nITlhWJNoac98u3TjVM8": [
            "28",
            "cc.Texture2D"
        ],
        "28gOIy9aFFSLrRuzIMYOzI": [
            "29",
            "cc.SpriteFrame",
            1
        ],
        "68m9A2Gk1ECaWLTwCtopIp": [
            "29",
            "cc.Texture2D"
        ],
        "2ffW7BiiVFL7eTWdtxmz1I": [
            "3",
            "cc.Texture2D"
        ],
        "e9+d2xDflHJ4m86yIu69b3": [
            "3",
            "cc.SpriteFrame",
            1
        ],
        "7ccgVgAzVPG7NogFFMy3/0": [
            "30",
            "cc.SpriteFrame",
            1
        ],
        "8b+RvsfWhIjYKttDOPtcSX": [
            "30",
            "cc.Texture2D"
        ],
        "0bsib2PVBDrKCrQqDz9eYG": [
            "31",
            "cc.SpriteFrame",
            1
        ],
        "9bPQ7BNb9J9qs1ERcpDApA": [
            "31",
            "cc.Texture2D"
        ],
        "53EqfuQzhPM7mi7Drsvvna": [
            "32",
            "cc.Texture2D"
        ],
        "f0NGnz8FhMNrF8G2lA45Zj": [
            "32",
            "cc.SpriteFrame",
            1
        ],
        "edzo9U0tVLOrTbn6lR+JeL": [
            "33",
            "cc.SpriteFrame",
            1
        ],
        "f6v1aSV7dOZarxZ4IrqgvO": [
            "33",
            "cc.Texture2D"
        ],
        "09NbNhcnFM7rZaMTW7tkOY": [
            "34",
            "cc.SpriteFrame",
            1
        ],
        "2ajPASWxZA+bGlu0tdrzF7": [
            "34",
            "cc.Texture2D"
        ],
        "05nE6DpgZDTK8a9s78wNZp": [
            "35",
            "cc.Texture2D"
        ],
        "a5eR76WhxPcJ69bbWisJDv": [
            "35",
            "cc.SpriteFrame",
            1
        ],
        "08mzfM1JdNzqa36XkH12pO": [
            "36",
            "cc.SpriteFrame",
            1
        ],
        "73STclRVJLCIOh7ZK3Oj+f": [
            "36",
            "cc.Texture2D"
        ],
        "40Mxc8QjdNc60pc9QJjgCR": [
            "37",
            "cc.Texture2D"
        ],
        "785OkoPitMZax8aXegeIw2": [
            "37",
            "cc.SpriteFrame",
            1
        ],
        "beQdxGftxGDL+434jtTHHq": [
            "38",
            "cc.SpriteFrame",
            1
        ],
        "d6yNmEknFBc5ny4+DseOD7": [
            "38",
            "cc.Texture2D"
        ],
        "18EwuJsX9O3avQ6jB7RazR": [
            "39",
            "cc.Texture2D"
        ],
        "27nOe3R2NI7If/p2meqw9R": [
            "39",
            "cc.SpriteFrame",
            1
        ],
        "10Cs1SJ7NMNKPLczBHOp7q": [
            "4",
            "cc.SpriteFrame",
            1
        ],
        "163k3w6ldOcL4xZ2EJuDwA": [
            "4",
            "cc.Texture2D"
        ],
        "45p7sVXhdHmpyLx7ZgAAHZ": [
            "40",
            "cc.SpriteFrame",
            1
        ],
        "d48SIshK9Fjq34kGM2yjb/": [
            "40",
            "cc.Texture2D"
        ],
        "a1J+MFRndG17A9RwqqoYA9": [
            "41",
            "cc.SpriteFrame",
            1
        ],
        "a8o4/itJhA6YTAxXGrwtjQ": [
            "41",
            "cc.Texture2D"
        ],
        "118XtQDjZBrpfEo6n6j5Io": [
            "42",
            "cc.Texture2D"
        ],
        "d2Qfde61RBHa6NX9mR6dqO": [
            "42",
            "cc.SpriteFrame",
            1
        ],
        "52kt8BQvhO7YgotO3yg4zq": [
            "43",
            "cc.Texture2D"
        ],
        "6dP9KAHbxO54gSa+MdnYr8": [
            "43",
            "cc.SpriteFrame",
            1
        ],
        "76PoXFVKNICpZMpjQcN/4A": [
            "44",
            "cc.SpriteFrame",
            1
        ],
        "ca4U+uQSRMa6PS1lTrr5Mk": [
            "44",
            "cc.Texture2D"
        ],
        "10gczhzd5BFakmrAKCNorO": [
            "45",
            "cc.SpriteFrame",
            1
        ],
        "63Oh3F4iRJ+qG7oU9d+sdJ": [
            "45",
            "cc.Texture2D"
        ],
        "501e9dAyVL5KxtiYbVkfXX": [
            "46",
            "cc.Texture2D"
        ],
        "d6nljL455CCI0Xn7nl+NxH": [
            "46",
            "cc.SpriteFrame",
            1
        ],
        "16Dmyg/5NIoJpev/pIK5hJ": [
            "47",
            "cc.Texture2D"
        ],
        "39k7yqQ21BcK1MaptA/a4l": [
            "47",
            "cc.SpriteFrame",
            1
        ],
        "97UmK6PhRJcqnLZihHE1vX": [
            "48",
            "cc.Texture2D"
        ],
        "bfzvrlUctMQrGL5VhONbIv": [
            "48",
            "cc.SpriteFrame",
            1
        ],
        "5fC53zdRlCBrFp3cCKqwU6": [
            "49",
            "cc.SpriteFrame",
            1
        ],
        "e0dVGVuO5GrJMNDgO3Co7/": [
            "49",
            "cc.Texture2D"
        ],
        "3a11Se4gBCwZjjEwExSsn0": [
            "5",
            "cc.SpriteFrame",
            1
        ],
        "bdDfOFIG9CUabx5lm+fqmS": [
            "5",
            "cc.Texture2D"
        ],
        "9aOxs1+ZtMq6hsfnTwRgSx": [
            "50",
            "cc.SpriteFrame",
            1
        ],
        "edWJwO0UpD/K6KaBZ01yyK": [
            "50",
            "cc.Texture2D"
        ],
        "10Qr3f+NZJOZtuytWFS/10": [
            "51",
            "cc.SpriteFrame",
            1
        ],
        "c1dG4aF85FGZyxrp+Ot+ZT": [
            "51",
            "cc.Texture2D"
        ],
        "1cSTO/YD9GZZynq2yr3D/h": [
            "52",
            "cc.Texture2D"
        ],
        "e8hL4kTKRE77KLiWc21ciC": [
            "52",
            "cc.SpriteFrame",
            1
        ],
        "c0u++dmxJPXqxysZOWyDjR": [
            "53",
            "cc.Texture2D"
        ],
        "e6TWPES8RB4LDdw4OHZscl": [
            "53",
            "cc.SpriteFrame",
            1
        ],
        "6aot3c1wFEh4QqhbHM7SAj": [
            "54",
            "cc.Texture2D"
        ],
        "a9lhxwjqVD15ehZ1i7Q0uU": [
            "54",
            "cc.SpriteFrame",
            1
        ],
        "68ibdxDsdKQoXDGqVCJGvx": [
            "6",
            "cc.Texture2D"
        ],
        "d1HBFIQplKQrFzm4BNzDon": [
            "6",
            "cc.SpriteFrame",
            1
        ],
        "25ux1QD+hLdaXFvgFJioF4": [
            "7",
            "cc.Texture2D"
        ],
        "edpmk6xIRPRKVzFcgVE6ZX": [
            "7",
            "cc.SpriteFrame",
            1
        ],
        "22EG/2UTtI4LQA/YgMZEHs": [
            "8",
            "cc.SpriteFrame",
            1
        ],
        "641vHysmVBh4i2L3bwf/ga": [
            "8",
            "cc.Texture2D"
        ],
        "4dAbGDtrJBq5TdnjNuS2IQ": [
            "9",
            "cc.SpriteFrame",
            1
        ],
        "83GFwpg5hCM7rqy0m5rqwh": [
            "9",
            "cc.Texture2D"
        ],
        "edQ3RF2rVDGaXbrteVaxK8": [
            "data",
            "cc.BufferAsset"
        ]
    },
    "uuids": [
        "029mfSeWdPUYrFiz8NBEjw",
        "04rbNfI4BAB4g2Cf863T3l",
        "05nE6DpgZDTK8a9s78wNZp",
        "08mzfM1JdNzqa36XkH12pO",
        "09NbNhcnFM7rZaMTW7tkOY",
        "0bsib2PVBDrKCrQqDz9eYG",
        "0d8BDS4TVMqIrXgAeDsDZ8",
        "10Cs1SJ7NMNKPLczBHOp7q",
        "10Qr3f+NZJOZtuytWFS/10",
        "10gczhzd5BFakmrAKCNorO",
        "10rv5DqDJIGL46tTev8SCq",
        "118XtQDjZBrpfEo6n6j5Io",
        "15IKLnjE5Pna+2Gxh7gNJh",
        "16Dmyg/5NIoJpev/pIK5hJ",
        "163k3w6ldOcL4xZ2EJuDwA",
        "18EwuJsX9O3avQ6jB7RazR",
        "1cSTO/YD9GZZynq2yr3D/h",
        "1c/GOmZglBn4LHA7+TTXy7",
        "1desLl4yhMka6fDT1yk90+",
        "22EG/2UTtI4LQA/YgMZEHs",
        "25ux1QD+hLdaXFvgFJioF4",
        "27nOe3R2NI7If/p2meqw9R",
        "28gOIy9aFFSLrRuzIMYOzI",
        "2ajPASWxZA+bGlu0tdrzF7",
        "2ffW7BiiVFL7eTWdtxmz1I",
        "32/qRABfZBlbui8CMzxz5l",
        "37voB+GNtJxqSy+7sneKHM",
        "39k7yqQ21BcK1MaptA/a4l",
        "3a11Se4gBCwZjjEwExSsn0",
        "3cFfAVcS5CILS8vlSS3NDZ",
        "40Mxc8QjdNc60pc9QJjgCR",
        "45p7sVXhdHmpyLx7ZgAAHZ",
        "48wUeKRBhGkpdXuN4MI8UM",
        "4aBvlIQeNK2IOBWmvKFO/m",
        "4dAbGDtrJBq5TdnjNuS2IQ",
        "4eeMFSptJO16KtzTB5ehB4",
        "501e9dAyVL5KxtiYbVkfXX",
        "52kt8BQvhO7YgotO3yg4zq",
        "53EqfuQzhPM7mi7Drsvvna",
        "58CLvVCTFLzpAswP5irm/d",
        "5btAs+DXVKjJ9LyOs+MUxI",
        "5d1E5yx/BEG4SS6TLAWvW7",
        "5fC53zdRlCBrFp3cCKqwU6",
        "61nITlhWJNoac98u3TjVM8",
        "63Oh3F4iRJ+qG7oU9d+sdJ",
        "64B7iS10pPMLYexhWjtQxU",
        "641vHysmVBh4i2L3bwf/ga",
        "66PVO8gr1IWbsPgcLgpNTy",
        "67BMUMPHlEUrV8gmysFDP6",
        "68ibdxDsdKQoXDGqVCJGvx",
        "68m9A2Gk1ECaWLTwCtopIp",
        "6aot3c1wFEh4QqhbHM7SAj",
        "6dP9KAHbxO54gSa+MdnYr8",
        "73STclRVJLCIOh7ZK3Oj+f",
        "76PoXFVKNICpZMpjQcN/4A",
        "785OkoPitMZax8aXegeIw2",
        "79oDw3Zm9IWaRk3EXpwRli",
        "79o3/Dd9VBvKaoCvNyDCrY",
        "7aoEcDVHFEUYN9aBpYO9oL",
        "7ccgVgAzVPG7NogFFMy3/0",
        "83GFwpg5hCM7rqy0m5rqwh",
        "8b+RvsfWhIjYKttDOPtcSX",
        "90p4iHfM5OC43LiybWaRKL",
        "97UmK6PhRJcqnLZihHE1vX",
        "98fK1Lq+FJAoRX+ZNGzb2j",
        "9aOxs1+ZtMq6hsfnTwRgSx",
        "9bPQ7BNb9J9qs1ERcpDApA",
        "9blsOIbrJIDKXRWtsW+jp1",
        "9eM3vLGlhAsreCsrG1DQ0M",
        "a1J+MFRndG17A9RwqqoYA9",
        "a5eR76WhxPcJ69bbWisJDv",
        "a8o4/itJhA6YTAxXGrwtjQ",
        "a9lhxwjqVD15ehZ1i7Q0uU",
        "acKpgN64xDXaZowa8i3vOM",
        "b3UKt2Z2xKYIC9E9/uxu9i",
        "b3871/jfBLMq96icCHyRzW",
        "bdDfOFIG9CUabx5lm+fqmS",
        "beQdxGftxGDL+434jtTHHq",
        "bfzvrlUctMQrGL5VhONbIv",
        "c0u++dmxJPXqxysZOWyDjR",
        "c1dG4aF85FGZyxrp+Ot+ZT",
        "c2Tn9h6aBC9ppfBhyaUO7A",
        "c3VjjUGW9B1ZhB45LePwCF",
        "c4P3/88sdFvKlp10TpQhd3",
        "ca4U+uQSRMa6PS1lTrr5Mk",
        "d1HBFIQplKQrFzm4BNzDon",
        "d2Qfde61RBHa6NX9mR6dqO",
        "d3BkeJwEZJaaXSHGAi2MrT",
        "d4sy5LaHNKVp4A9DeZg3yq",
        "d48SIshK9Fjq34kGM2yjb/",
        "d58n5dGu5Kn4BbTb5V4Efn",
        "d6nljL455CCI0Xn7nl+NxH",
        "d6yNmEknFBc5ny4+DseOD7",
        "e0dVGVuO5GrJMNDgO3Co7/",
        "e6TWPES8RB4LDdw4OHZscl",
        "e8hL4kTKRE77KLiWc21ciC",
        "e9+d2xDflHJ4m86yIu69b3",
        "edNqTdobFC9Knh8IuotWbn",
        "edQ3RF2rVDGaXbrteVaxK8",
        "edWJwO0UpD/K6KaBZ01yyK",
        "edpmk6xIRPRKVzFcgVE6ZX",
        "edzo9U0tVLOrTbn6lR+JeL",
        "efDPacnAVLpoQ5S0Ovh1Nv",
        "f0NGnz8FhMNrF8G2lA45Zj",
        "f2RoUEDfNAq7vEst/bvQ9e",
        "f3am8IdzhA2ayzpz6KNhPO",
        "f6v1aSV7dOZarxZ4IrqgvO",
        "f7YOiOWV5NtJegf7GZRQiw",
        "fcSD5HxXdFUpXBfnlIF/tT"
    ],
    "scenes": {},
    "redirect": [],
    "deps": [],
    "packs": {
        "02902278a": [
            "04rbNfI4BAB4g2Cf863T3l",
            "05nE6DpgZDTK8a9s78wNZp",
            "0d8BDS4TVMqIrXgAeDsDZ8",
            "118XtQDjZBrpfEo6n6j5Io",
            "15IKLnjE5Pna+2Gxh7gNJh",
            "16Dmyg/5NIoJpev/pIK5hJ",
            "163k3w6ldOcL4xZ2EJuDwA",
            "18EwuJsX9O3avQ6jB7RazR",
            "1cSTO/YD9GZZynq2yr3D/h",
            "1c/GOmZglBn4LHA7+TTXy7",
            "25ux1QD+hLdaXFvgFJioF4",
            "2ajPASWxZA+bGlu0tdrzF7",
            "2ffW7BiiVFL7eTWdtxmz1I",
            "37voB+GNtJxqSy+7sneKHM",
            "3cFfAVcS5CILS8vlSS3NDZ",
            "40Mxc8QjdNc60pc9QJjgCR",
            "4eeMFSptJO16KtzTB5ehB4",
            "501e9dAyVL5KxtiYbVkfXX",
            "52kt8BQvhO7YgotO3yg4zq",
            "53EqfuQzhPM7mi7Drsvvna",
            "5d1E5yx/BEG4SS6TLAWvW7",
            "61nITlhWJNoac98u3TjVM8",
            "63Oh3F4iRJ+qG7oU9d+sdJ",
            "64B7iS10pPMLYexhWjtQxU",
            "641vHysmVBh4i2L3bwf/ga",
            "66PVO8gr1IWbsPgcLgpNTy",
            "67BMUMPHlEUrV8gmysFDP6",
            "68ibdxDsdKQoXDGqVCJGvx",
            "68m9A2Gk1ECaWLTwCtopIp",
            "6aot3c1wFEh4QqhbHM7SAj",
            "73STclRVJLCIOh7ZK3Oj+f",
            "79oDw3Zm9IWaRk3EXpwRli",
            "83GFwpg5hCM7rqy0m5rqwh",
            "8b+RvsfWhIjYKttDOPtcSX",
            "97UmK6PhRJcqnLZihHE1vX",
            "9bPQ7BNb9J9qs1ERcpDApA",
            "9eM3vLGlhAsreCsrG1DQ0M",
            "a8o4/itJhA6YTAxXGrwtjQ",
            "b3UKt2Z2xKYIC9E9/uxu9i",
            "bdDfOFIG9CUabx5lm+fqmS",
            "c0u++dmxJPXqxysZOWyDjR",
            "c1dG4aF85FGZyxrp+Ot+ZT",
            "c2Tn9h6aBC9ppfBhyaUO7A",
            "ca4U+uQSRMa6PS1lTrr5Mk",
            "d48SIshK9Fjq34kGM2yjb/",
            "d58n5dGu5Kn4BbTb5V4Efn",
            "d6yNmEknFBc5ny4+DseOD7",
            "e0dVGVuO5GrJMNDgO3Co7/",
            "edNqTdobFC9Knh8IuotWbn",
            "edWJwO0UpD/K6KaBZ01yyK",
            "f2RoUEDfNAq7vEst/bvQ9e",
            "f3am8IdzhA2ayzpz6KNhPO",
            "f6v1aSV7dOZarxZ4IrqgvO",
            "fcSD5HxXdFUpXBfnlIF/tT"
        ]
    },
    "name": "116",
    "importBase": "import",
    "nativeBase": "native",
    "debug": true,
    "isZip": false,
    "encrypted": false,
    "versions": {
        "import": [
            "02902278a",
            "7061d",
            "029mfSeWdPUYrFiz8NBEjw",
            "e9e85",
            "08mzfM1JdNzqa36XkH12pO",
            "e9a72",
            "09NbNhcnFM7rZaMTW7tkOY",
            "b8188",
            "0bsib2PVBDrKCrQqDz9eYG",
            "7ac45",
            "10Cs1SJ7NMNKPLczBHOp7q",
            "62f3b",
            "10Qr3f+NZJOZtuytWFS/10",
            "020e0",
            "10gczhzd5BFakmrAKCNorO",
            "3796c",
            "10rv5DqDJIGL46tTev8SCq",
            "745f3",
            "1desLl4yhMka6fDT1yk90+",
            "8ca56",
            "22EG/2UTtI4LQA/YgMZEHs",
            "f786a",
            "27nOe3R2NI7If/p2meqw9R",
            "e1e41",
            "28gOIy9aFFSLrRuzIMYOzI",
            "196ee",
            "32/qRABfZBlbui8CMzxz5l",
            "95179",
            "39k7yqQ21BcK1MaptA/a4l",
            "348e8",
            "3a11Se4gBCwZjjEwExSsn0",
            "6549d",
            "45p7sVXhdHmpyLx7ZgAAHZ",
            "36bf8",
            "48wUeKRBhGkpdXuN4MI8UM",
            "99185",
            "4aBvlIQeNK2IOBWmvKFO/m",
            "41582",
            "4dAbGDtrJBq5TdnjNuS2IQ",
            "66594",
            "58CLvVCTFLzpAswP5irm/d",
            "e66f3",
            "5btAs+DXVKjJ9LyOs+MUxI",
            "d46b9",
            "5fC53zdRlCBrFp3cCKqwU6",
            "1fdff",
            "6dP9KAHbxO54gSa+MdnYr8",
            "3ff42",
            "76PoXFVKNICpZMpjQcN/4A",
            "b3a36",
            "785OkoPitMZax8aXegeIw2",
            "d52f1",
            "79o3/Dd9VBvKaoCvNyDCrY",
            "c650b",
            "7aoEcDVHFEUYN9aBpYO9oL",
            "2b5cc",
            "7ccgVgAzVPG7NogFFMy3/0",
            "c4ea6",
            "90p4iHfM5OC43LiybWaRKL",
            "cff09",
            "98fK1Lq+FJAoRX+ZNGzb2j",
            "ebfc6",
            "9aOxs1+ZtMq6hsfnTwRgSx",
            "0268d",
            "9blsOIbrJIDKXRWtsW+jp1",
            "7e983",
            "a1J+MFRndG17A9RwqqoYA9",
            "35c2d",
            "a5eR76WhxPcJ69bbWisJDv",
            "aa65f",
            "a9lhxwjqVD15ehZ1i7Q0uU",
            "6ca41",
            "acKpgN64xDXaZowa8i3vOM",
            "a63ad",
            "b3871/jfBLMq96icCHyRzW",
            "36923",
            "beQdxGftxGDL+434jtTHHq",
            "6522b",
            "bfzvrlUctMQrGL5VhONbIv",
            "40deb",
            "c3VjjUGW9B1ZhB45LePwCF",
            "03415",
            "c4P3/88sdFvKlp10TpQhd3",
            "b30fb",
            "d1HBFIQplKQrFzm4BNzDon",
            "8aea8",
            "d2Qfde61RBHa6NX9mR6dqO",
            "d07f2",
            "d3BkeJwEZJaaXSHGAi2MrT",
            "0c58c",
            "d4sy5LaHNKVp4A9DeZg3yq",
            "c3193",
            "d6nljL455CCI0Xn7nl+NxH",
            "49a35",
            "e6TWPES8RB4LDdw4OHZscl",
            "8f5d9",
            "e8hL4kTKRE77KLiWc21ciC",
            "8d2e0",
            "e9+d2xDflHJ4m86yIu69b3",
            "46d14",
            "edQ3RF2rVDGaXbrteVaxK8",
            "32a02",
            "edpmk6xIRPRKVzFcgVE6ZX",
            "0611e",
            "edzo9U0tVLOrTbn6lR+JeL",
            "211d4",
            "efDPacnAVLpoQ5S0Ovh1Nv",
            "b41de",
            "f0NGnz8FhMNrF8G2lA45Zj",
            "bdbd7",
            "f7YOiOWV5NtJegf7GZRQiw",
            "30a91"
        ],
        "native": [
            "04rbNfI4BAB4g2Cf863T3l",
            "73411",
            "05nE6DpgZDTK8a9s78wNZp",
            "be871",
            "0d8BDS4TVMqIrXgAeDsDZ8",
            "013ed",
            "118XtQDjZBrpfEo6n6j5Io",
            "c97e0",
            "15IKLnjE5Pna+2Gxh7gNJh",
            "ae45f",
            "16Dmyg/5NIoJpev/pIK5hJ",
            "47655",
            "163k3w6ldOcL4xZ2EJuDwA",
            "2145f",
            "18EwuJsX9O3avQ6jB7RazR",
            "86076",
            "1cSTO/YD9GZZynq2yr3D/h",
            "3c0e1",
            "1c/GOmZglBn4LHA7+TTXy7",
            "b4dcb",
            "25ux1QD+hLdaXFvgFJioF4",
            "2f4e5",
            "2ajPASWxZA+bGlu0tdrzF7",
            "6b442",
            "2ffW7BiiVFL7eTWdtxmz1I",
            "d557d",
            "37voB+GNtJxqSy+7sneKHM",
            "5234c",
            "3cFfAVcS5CILS8vlSS3NDZ",
            "f91e7",
            "40Mxc8QjdNc60pc9QJjgCR",
            "62a74",
            "4eeMFSptJO16KtzTB5ehB4",
            "de8a2",
            "501e9dAyVL5KxtiYbVkfXX",
            "15a55",
            "52kt8BQvhO7YgotO3yg4zq",
            "e631c",
            "53EqfuQzhPM7mi7Drsvvna",
            "abfe6",
            "5d1E5yx/BEG4SS6TLAWvW7",
            "7a9aa",
            "61nITlhWJNoac98u3TjVM8",
            "057a9",
            "63Oh3F4iRJ+qG7oU9d+sdJ",
            "4aada",
            "64B7iS10pPMLYexhWjtQxU",
            "42e5e",
            "641vHysmVBh4i2L3bwf/ga",
            "dd1d1",
            "66PVO8gr1IWbsPgcLgpNTy",
            "cadbc",
            "67BMUMPHlEUrV8gmysFDP6",
            "e6524",
            "68ibdxDsdKQoXDGqVCJGvx",
            "51258",
            "68m9A2Gk1ECaWLTwCtopIp",
            "82ea3",
            "6aot3c1wFEh4QqhbHM7SAj",
            "3d532",
            "73STclRVJLCIOh7ZK3Oj+f",
            "43be8",
            "79oDw3Zm9IWaRk3EXpwRli",
            "31d66",
            "83GFwpg5hCM7rqy0m5rqwh",
            "33ac0",
            "8b+RvsfWhIjYKttDOPtcSX",
            "1142b",
            "97UmK6PhRJcqnLZihHE1vX",
            "f2720",
            "9bPQ7BNb9J9qs1ERcpDApA",
            "4b35f",
            "9eM3vLGlhAsreCsrG1DQ0M",
            "3dd71",
            "a8o4/itJhA6YTAxXGrwtjQ",
            "c7088",
            "b3UKt2Z2xKYIC9E9/uxu9i",
            "7b289",
            "bdDfOFIG9CUabx5lm+fqmS",
            "adad2",
            "c0u++dmxJPXqxysZOWyDjR",
            "9c8d0",
            "c1dG4aF85FGZyxrp+Ot+ZT",
            "35c9b",
            "c2Tn9h6aBC9ppfBhyaUO7A",
            "829a4",
            "ca4U+uQSRMa6PS1lTrr5Mk",
            "5e2df",
            "d48SIshK9Fjq34kGM2yjb/",
            "9e100",
            "d58n5dGu5Kn4BbTb5V4Efn",
            "fd9a8",
            "d6yNmEknFBc5ny4+DseOD7",
            "f896b",
            "e0dVGVuO5GrJMNDgO3Co7/",
            "d3c5b",
            "edNqTdobFC9Knh8IuotWbn",
            "ff5f2",
            "edQ3RF2rVDGaXbrteVaxK8",
            "da4ae",
            "edWJwO0UpD/K6KaBZ01yyK",
            "b16e6",
            "f2RoUEDfNAq7vEst/bvQ9e",
            "41611",
            "f3am8IdzhA2ayzpz6KNhPO",
            "299a3",
            "f6v1aSV7dOZarxZ4IrqgvO",
            "74362",
            "fcSD5HxXdFUpXBfnlIF/tT",
            "2841b"
        ]
    }
}